signup_genius/__init__.py
signup_genius/api.py
signup_genius/enums.py
signup_genius/errors.py
signup_genius/fixes.py
signup_genius/introspect.py
signup_genius/name_mapping.py
signup_genius/signup.py
signup_genius/utils.py
signup_genius/parsers/__init__.py
signup_genius/parsers/date_location_time_slot.py
signup_genius/parsers/date_time_slot.py
signup_genius/parsers/rsvp.py
signup_genius/parsers/rsvp_adult_child.py
signup_genius/parsers/slot_datetime.py
signup_genius-0.0.10.dist-info/LICENSE
signup_genius-0.0.10.dist-info/METADATA
signup_genius-0.0.10.dist-info/WHEEL
signup_genius-0.0.10.dist-info/top_level.txt
signup_genius-0.0.10.dist-info/RECORD
