Metadata-Version: 2.1
Name: signup-genius
Version: 0.0.10
Summary: A package to parse sign up genius form responses
Author-email: David Feeley <davidpfeeley@gmail.com>
Project-URL: Homepage, https://github.com/dfeeley/signup-genius
Project-URL: Bug Tracker, https://github.com/dfeeley/signup-genius/issues
Classifier: Programming Language :: Python :: 3
Classifier: License :: OSI Approved :: MIT License
Classifier: Operating System :: OS Independent
Requires-Python: >=3.9
License-File: LICENSE
Requires-Dist: beautifulsoup4
Requires-Dist: levenshtein
Requires-Dist: requests
Requires-Dist: python-dateutil
